README.md
setup.cfg
setup.py
gaussian_binomial_distributions_bkim00/Binomialdistribution.py
gaussian_binomial_distributions_bkim00/Gaussiandistribution.py
gaussian_binomial_distributions_bkim00/Generaldistribution.py
gaussian_binomial_distributions_bkim00/__init__.py
gaussian_binomial_distributions_bkim00.egg-info/PKG-INFO
gaussian_binomial_distributions_bkim00.egg-info/SOURCES.txt
gaussian_binomial_distributions_bkim00.egg-info/dependency_links.txt
gaussian_binomial_distributions_bkim00.egg-info/not-zip-safe
gaussian_binomial_distributions_bkim00.egg-info/top_level.txt