Metadata-Version: 1.0
Name: gaussian-binomial-distributions-bkim00
Version: 0.1
Summary: Gaussian and Binomial distributions
Home-page: UNKNOWN
Author: Byungjin Kim
Author-email: bkim0018@gmail.com
License: UNKNOWN
Platform: UNKNOWN
